testapp_ualsg/__init__.py
testapp_ualsg/testapp_ualsg.py
testapp_ualsg-0.1.0.dist-info/LICENSE
testapp_ualsg-0.1.0.dist-info/WHEEL
testapp_ualsg-0.1.0.dist-info/METADATA
testapp_ualsg-0.1.0.dist-info/RECORD
